{
  "context": {
    "id": "0",
    "source": "/github",
    "timestamp": "2025-01-22T19:03:50+00:00",
    "type": "dev.cdevents.pipelinerun.finished.0.2.0",
    "version": "0.4.1"
  },
  "customData": {
    "github": {
      "repository": {
        "url": "https://api.github.com/repos/aaaaa-aaa/aaaaa-aaaaaaaaa"
      },
      "sender": {
        "login": "aaaaaA"
      }
    }
  },
  "subject": {
    "content": {
      "outcome": "success",
      "pipelineName": "aaaaa-aaa/aaaaa-aaaaaaaaa/aa",
      "url": "https://github.com/aaaaa-aaa/aaaaa-aaaaaaaaa/actions/runs/11111111111/attempts/1"
    },
    "id": "https://api.github.com/repos/aaaaa-aaa/aaaaa-aaaaaaaaa/actions/runs/11111111111/attempts/1",
    "type": "pipelineRun"
  }
}